dimcli/__init__.py
dimcli/cliparse.py
dimcli/version.py
dimcli/zonedelete.py
dimcli/zoneimport.py
dimclient_cli-5.0.4.post1.dist-info/METADATA
dimclient_cli-5.0.4.post1.dist-info/WHEEL
dimclient_cli-5.0.4.post1.dist-info/entry_points.txt
dimclient_cli-5.0.4.post1.dist-info/top_level.txt
dimclient_cli-5.0.4.post1.dist-info/RECORD
