Metadata-Version: 2.4
Name: dimclient-cli
Version: 5.0.4.post1
Summary: DNS and IP management Python CLI client
Maintainer: zerimond
Project-URL: Homepage, https://github.com/ionos-cloud/dim
Project-URL: Issues, https://github.com/ionos-cloud/dim/issues
Classifier: Development Status :: 5 - Production/Stable
Classifier: Intended Audience :: System Administrators
Classifier: Programming Language :: Python :: 3
Classifier: License :: OSI Approved :: MIT License
Classifier: Operating System :: OS Independent
Requires-Python: >=3.6
Requires-Dist: dimclient
Requires-Dist: python-dateutil>=1.4.1
Requires-Dist: dnspython!=2.2.0,>=1.12.0
Provides-Extra: docs
Requires-Dist: Sphinx~=4.4; extra == "docs"
Requires-Dist: hypothesis~=5.6.0; extra == "docs"
